zombie_nomnom_api-1.0.0.dist-info/METADATA
zombie_nomnom_api-1.0.0.dist-info/WHEEL
zombie_nomnom_api-1.0.0.dist-info/entry_points.txt
zombie_nomnom_api-1.0.0.dist-info/licenses/LICENSE
zombie_nomnom_api/__init__.py
zombie_nomnom_api/__main__.py
zombie_nomnom_api/app.py
zombie_nomnom_api/game.py
zombie_nomnom_api/graphql_app/__init__.py
zombie_nomnom_api/graphql_app/app.py
zombie_nomnom_api/graphql_app/dependencies.py
zombie_nomnom_api/graphql_app/resolvers.py
zombie_nomnom_api/graphql_app/schema.gql
zombie_nomnom_api/graphql_app/schema.py
zombie_nomnom_api/server.py
zombie_nomnom_api-1.0.0.dist-info/RECORD
