Metadata-Version: 2.1
Name: zombie_nomnom_api
Version: 1.0.0
Summary: An API for the zombie-nomnom pypi package exposing functionality via a graphql api.
Keywords: game,api,dice
Author-Email: Andres Carrera <andreshcar@live.com>
Classifier: Intended Audience :: Information Technology
Classifier: Intended Audience :: Developers
Classifier: Operating System :: OS Independent
Classifier: Topic :: Software Development :: Libraries :: Python Modules
Classifier: Topic :: Software Development :: Libraries
Classifier: Topic :: Software Development
Classifier: License :: OSI Approved :: MIT License
Classifier: Programming Language :: Python :: 3 :: Only
Classifier: Programming Language :: Python :: 3.10
Classifier: Programming Language :: Python :: 3.11
Classifier: Programming Language :: Python :: 3.12
Project-URL: Homepage, https://github.com/carrera-dev-consulting/zombie-nomnom-api
Project-URL: Documentation, https://consulting.gxldcptrick.dev/zombie-nomnom-api/docs
Project-URL: Repository, https://github.com/carrera-dev-consulting/zombie-nomnom-api
Project-URL: Issues, https://github.com/carrera-dev-consulting/zombie-nomnom-api/issues
Project-URL: Changelog, https://github.com/carrera-dev-consulting/zombie-nomnom-api/releases
Requires-Python: >=3.10
Requires-Dist: zombie-nomnom>=0.3.0
Requires-Dist: click>=8.1.7
Requires-Dist: fastapi>=0.115.0
Requires-Dist: uvicorn>=0.31.1
Requires-Dist: ariadne>=0.23.0
Requires-Dist: pydantic-settings>=2.6.1
